Metadata-Version: 2.1
Name: discord-requests-lib
Version: 1.0.1
Summary: Simplification of all discord API requests.
Author: Benjamin Rodriguez
Author-email: benjaminrodriguezshhh@proton.me
